pystratis/__init__.py
pystratis/api/__init__.py
pystratis/api/apierror.py
pystratis/api/apirequest.py
pystratis/api/endpoint_register.py
pystratis/api/featureinitializationstate.py
pystratis/api/fullnodestate.py
pystratis/api/logrule.py
pystratis/api/model.py
pystratis/api/addressbook/__init__.py
pystratis/api/addressbook/addressbook.py
pystratis/api/addressbook/requestmodels/__init__.py
pystratis/api/addressbook/requestmodels/addrequest.py
pystratis/api/addressbook/requestmodels/getrequest.py
pystratis/api/addressbook/requestmodels/removerequest.py
pystratis/api/addressbook/responsemodels/__init__.py
pystratis/api/addressbook/responsemodels/addressbookentrymodel.py
pystratis/api/balances/__init__.py
pystratis/api/balances/balances.py
pystratis/api/balances/requestmodels/__init__.py
pystratis/api/balances/requestmodels/overamountatheightrequest.py
pystratis/api/blockstore/__init__.py
pystratis/api/blockstore/blockstore.py
pystratis/api/blockstore/requestmodels/__init__.py
pystratis/api/blockstore/requestmodels/blockrequest.py
pystratis/api/blockstore/requestmodels/getaddressesbalancesrequest.py
pystratis/api/blockstore/requestmodels/getlastbalanceupdatetransactionrequest.py
pystratis/api/blockstore/requestmodels/getutxosetforaddressrequest.py
pystratis/api/blockstore/requestmodels/getutxosetrequest.py
pystratis/api/blockstore/requestmodels/getverboseaddressesbalancesrequest.py
pystratis/api/blockstore/responsemodels/__init__.py
pystratis/api/blockstore/responsemodels/addressbalancemodel.py
pystratis/api/blockstore/responsemodels/addressindexertipmodel.py
pystratis/api/blockstore/responsemodels/balancechangesmodel.py
pystratis/api/blockstore/responsemodels/getaddressesbalancesmodel.py
pystratis/api/blockstore/responsemodels/getlastbalanceupdatetransactionmodel.py
pystratis/api/blockstore/responsemodels/getutxosforaddressmodel.py
pystratis/api/blockstore/responsemodels/getverboseaddressesbalancesmodel.py
pystratis/api/blockstore/responsemodels/utxomodel.py
pystratis-1.1.2.1.dist-info/LICENSE
pystratis-1.1.2.1.dist-info/METADATA
pystratis-1.1.2.1.dist-info/WHEEL
pystratis-1.1.2.1.dist-info/top_level.txt
pystratis-1.1.2.1.dist-info/zip-safe
pystratis-1.1.2.1.dist-info/RECORD
