Metadata-Version: 2.1
Name: pystratis
Version: 1.1.2.1
Summary: Official python package for interacting with Stratis (STRAX) full node and Cirrus/Interflux sidechain.
Home-page: https://github.com/stratisproject/pystratis
Author: Tjaden Froyda, Stratis Platform
Author-email: support@stratisplatform.com
License: MIT
Keywords: stratis,cirrus,pystratis,smartcontracts,blockchain
Classifier: Development Status :: 5 - Production/Stable
Classifier: Intended Audience :: Developers
Classifier: License :: OSI Approved :: MIT License
Classifier: Programming Language :: Python :: 3.7
Classifier: Programming Language :: Python :: 3.8
Classifier: Programming Language :: Python :: 3.9
Classifier: Programming Language :: Python :: 3.10
Classifier: Programming Language :: Python :: 3.11
Requires-Python: <4,>=3.7
License-File: LICENSE
Requires-Dist: requests
Requires-Dist: pydantic (>=1.8.2)
Requires-Dist: base58
Requires-Dist: base58check
Requires-Dist: bech32
Requires-Dist: loguru
Provides-Extra: test
Requires-Dist: pytest ; extra == 'test'
Requires-Dist: pytest-mock ; extra == 'test'
Requires-Dist: pytest-order ; extra == 'test'
Requires-Dist: pytest-timetout ; extra == 'test'
Requires-Dist: coverage ; extra == 'test'
Requires-Dist: ecdsa ; extra == 'test'
Requires-Dist: mnemonic ; extra == 'test'
